openfga_sdk/__init__.py
openfga_sdk/api_client.py
openfga_sdk/configuration.py
openfga_sdk/constants.py
openfga_sdk/credentials.py
openfga_sdk/exceptions.py
openfga_sdk/help.py
openfga_sdk/oauth2.py
openfga_sdk/rest.py
openfga_sdk/validation.py
openfga_sdk/api/__init__.py
openfga_sdk/api/open_fga_api.py
openfga_sdk/client/__init__.py
openfga_sdk/client/client.py
openfga_sdk/client/configuration.py
openfga_sdk/client/models/__init__.py
openfga_sdk/client/models/assertion.py
openfga_sdk/client/models/batch_check_item.py
openfga_sdk/client/models/batch_check_request.py
openfga_sdk/client/models/batch_check_response.py
openfga_sdk/client/models/batch_check_single_response.py
openfga_sdk/client/models/check_request.py
openfga_sdk/client/models/client_batch_check_response.py
openfga_sdk/client/models/expand_request.py
openfga_sdk/client/models/list_objects_request.py
openfga_sdk/client/models/list_relations_request.py
openfga_sdk/client/models/list_users_request.py
openfga_sdk/client/models/read_changes_request.py
openfga_sdk/client/models/tuple.py
openfga_sdk/client/models/write_conflict_opts.py
openfga_sdk/client/models/write_options.py
openfga_sdk/client/models/write_request.py
openfga_sdk/client/models/write_response.py
openfga_sdk/client/models/write_single_response.py
openfga_sdk/client/models/write_transaction_opts.py
openfga_sdk/models/__init__.py
openfga_sdk/models/aborted_message_response.py
openfga_sdk/models/any.py
openfga_sdk/models/assertion.py
openfga_sdk/models/assertion_tuple_key.py
openfga_sdk/models/auth_error_code.py
openfga_sdk/models/authorization_model.py
openfga_sdk/models/batch_check_item.py
openfga_sdk/models/batch_check_request.py
openfga_sdk/models/batch_check_response.py
openfga_sdk/models/batch_check_single_result.py
openfga_sdk/models/check_error.py
openfga_sdk/models/check_request.py
openfga_sdk/models/check_request_tuple_key.py
openfga_sdk/models/check_response.py
openfga_sdk/models/computed.py
openfga_sdk/models/condition.py
openfga_sdk-0.9.9.dist-info/METADATA
openfga_sdk-0.9.9.dist-info/WHEEL
openfga_sdk-0.9.9.dist-info/licenses/LICENSE
openfga_sdk-0.9.9.dist-info/RECORD
