Metadata-Version: 2.4
Name: openfga-sdk
Version: 0.9.9
Summary: A high performance and flexible authorization/permission engine built for developers and inspired by Google Zanzibar.
Project-URL: Repository, https://github.com/openfga/python-sdk.git
Author-email: "OpenFGA (https://openfga.dev)" <community@openfga.dev>
License-Expression: Apache-2.0
License-File: LICENSE
Keywords: authorization,fga,fine-grained-authorization,openfga,rebac,zanzibar
Classifier: Development Status :: 5 - Production/Stable
Classifier: Intended Audience :: Developers
Classifier: License :: OSI Approved :: Apache Software License
Classifier: Programming Language :: Python :: 3.10
Classifier: Programming Language :: Python :: 3.11
Classifier: Programming Language :: Python :: 3.12
Requires-Python: >=3.10
Requires-Dist: aiohttp>=3.9.3
Requires-Dist: opentelemetry-api>=1.25.0
Requires-Dist: python-dateutil>=2.9.0
Requires-Dist: urllib3<3,>=1.26.19
